pymotherless.py
PyMotherless-0.4.7.data/scripts/pymotherless-demo.py
PyMotherless-0.4.7.data/scripts/pymotherless-dl.py
PyMotherless-0.4.7.data/scripts/pymotherless-httpd.py
PyMotherless-0.4.7.dist-info/LICENSE
PyMotherless-0.4.7.dist-info/METADATA
PyMotherless-0.4.7.dist-info/WHEEL
PyMotherless-0.4.7.dist-info/top_level.txt
PyMotherless-0.4.7.dist-info/zip-safe
PyMotherless-0.4.7.dist-info/RECORD
