Metadata-Version: 2.1
Name: PyMotherless
Version: 0.4.7
Summary: Get urls of images/videos from motherless.
Home-page: https://github.com/GameMaker2k/PyMotherless
Author: Kazuki Przyborowski
Author-email: kazuki.przyborowski@gmail.com
Maintainer: Kazuki Przyborowski
Maintainer-email: kazuki.przyborowski@gmail.com
License: Revised BSD License
Download-URL: https://github.com/GameMaker2k/PyMotherless/archive/master.tar.gz
Keywords: motherless pymotherless python python-motherless
Platform: OS Independent
Classifier: Development Status :: 5 - Production/Stable
Classifier: Intended Audience :: Developers
Classifier: Intended Audience :: Other Audience
Classifier: License :: OSI Approved
Classifier: License :: OSI Approved :: BSD License
Classifier: Natural Language :: English
Classifier: Operating System :: MacOS
Classifier: Operating System :: MacOS :: MacOS X
Classifier: Operating System :: Microsoft
Classifier: Operating System :: Microsoft :: Windows
Classifier: Operating System :: OS/2
Classifier: Operating System :: OS Independent
Classifier: Operating System :: POSIX
Classifier: Operating System :: Unix
Classifier: Programming Language :: Python
Classifier: Topic :: Utilities
Classifier: Topic :: Software Development
Classifier: Topic :: Software Development :: Libraries
Classifier: Topic :: Software Development :: Libraries :: Python Modules
